{
    "Description": "ru",
    "TutorialVideos" : ["video_help_11", "video_help_22", "video_help_33"],
    "Levels": {
        "1": "Ru_1",
        "2": "Ru_2",
        "3": "Ru_3",
        "4": "Ru_4",
        "5": "Ru_5",
        "6": "Ru_6",
        "7": "Ru_7",
        "8": "Ru_8",
        "9": "Ru_9",
        "10": "Ru_10",
        "11": "Ru_11",
        "12": "Ru_12",
        "13": "Ru_13",
        "14": "Ru_14",
        "15": "Ru_15",
        "16": "Ru_16",
        "17": "Ru_17",
        "18": "Ru_18",
        "19": "Ru_19",
        "20": "Ru_20",
        "21": "Ru_21",
        "22": "Ru_22",
        "23": "Ru_23",
        "24": "Ru_24",
        "25": "Ru_25",
        "26": "Ru_26",
        "27": "Ru_27",
        "28": "Ru_28",
        "29": "Ru_29",
        "30": "Ru_30",
        "31": "Ru_31",
        "32": "Ru_32",
        "33": "Ru_33",
        "34": "Ru_34",
        "35": "Ru_35",
        "36": "Ru_36",
        "37": "Ru_37",
        "38": "Ru_38",
        "39": "Ru_39",
        "40": "Ru_40",
        "41": "Ru_41",
        "42": "Ru_42",
        "43": "Ru_43",
        "44": "Ru_44",
        "45": "Ru_45",
        "46": "Ru_46",
        "47": "Ru_47",
        "48": "Ru_48",
        "49": "Ru_49",
        "50": "Ru_50",
        "51": "Ru_51",
        "52": "Ru_52",
        "53": "Ru_53",
        "54": "Ru_54",
        "55": "Ru_55",
        "56": "Ru_56",
        "57": "Ru_57",
        "58": "Ru_58",
        "59": "Ru_59",
        "60": "Ru_60",
        "61": "Ru_61",
        "62": "Ru_62",
        "63": "Ru_63",
        "64": "Ru_64",
        "65": "Ru_65",
        "66": "Ru_66",
        "67": "Ru_67",
        "68": "Ru_68",
        "69": "Ru_69",
        "70": "Ru_70",
        "71": "Ru_71",
        "72": "Ru_72",
        "73": "Ru_73",
        "74": "Ru_74",
        "75": "Ru_75",
        "76": "Ru_76",
        "77": "Ru_77",
        "78": "Ru_78",
        "79": "Ru_79",
        "80": "Ru_80",
        "81": "Ru_81",
        "82": "Ru_82",
        "83": "Ru_83",
        "84": "Ru_84",
        "85": "Ru_85",
        "86": "Ru_86",
        "87": "Ru_87",
        "88": "Ru_88",
        "89": "Ru_89",
        "90": "Ru_90",
        "91": "Ru_91",
        "92": "Ru_92",
        "93": "Ru_93",
        "94": "Ru_94",
        "95": "Ru_95",
        "96": "Ru_96",
        "97": "Ru_97",
        "98": "Ru_98",
        "99": "Ru_99",
        "100": "Ru_100",
        "101": "Ru_101",
        "102": "Ru_102",
        "103": "Ru_103",
        "104": "Ru_104",
        "105": "Ru_105",
        "106": "Ru_106",
        "107": "Ru_107",
        "108": "Ru_108",
        "109": "Ru_109",
        "110": "Ru_110",
        "111": "Ru_111",
        "112": "Ru_112",
        "113": "Ru_113",
        "114": "Ru_114",
        "115": "Ru_115",
        "116": "Ru_116",
        "117": "Ru_117",
        "118": "Ru_118",
        "119": "Ru_119",
        "120": "Ru_120",
        "121": "Ru_121",
        "122": "Ru_122",
        "123": "Ru_123",
        "124": "Ru_124",
        "125": "Ru_125",
        "126": "Ru_126",
        "127": "Ru_127",
        "128": "Ru_128",
        "129": "Ru_129",
        "130": "Ru_130",
        "131": "Ru_131",
        "132": "Ru_132",
        "133": "Ru_133",
        "134": "Ru_134",
        "135": "Ru_135",
        "136": "Ru_136",
        "137": "Ru_137",
        "138": "Ru_138",
        "139": "Ru_139",
        "140": "Ru_140",
        "141": "Ru_141",
        "142": "Ru_142",
        "143": "Ru_143",
        "144": "Ru_144",
        "145": "Ru_145",
        "146": "Ru_146",
        "147": "Ru_147",
        "148": "Ru_148",
        "149": "Ru_149",
        "150": "Ru_150",
        "151": "Ru_151",
        "152": "Ru_152",
        "153": "Ru_153",
        "154": "Ru_154",
        "155": "Ru_155",
        "156": "Ru_156",
        "157": "Ru_157",
        "158": "Ru_158",
        "159": "Ru_159",
        "160": "Ru_160",
        "161": "Ru_161",
        "162": "Ru_162",
        "163": "Ru_163",
        "164": "Ru_164",
        "165": "Ru_165",
        "166": "Ru_166",
        "167": "Ru_167",
        "168": "Ru_168",
        "169": "Ru_169",
        "170": "Ru_170",
        "171": "Ru_171",
        "172": "Ru_172",
        "173": "Ru_173",
        "174": "Ru_174",
        "175": "Ru_175",
        "176": "Ru_176",
        "177": "Ru_177",
        "178": "Ru_178",
        "179": "Ru_179",
        "180": "Ru_180",
        "181": "Ru_181",
        "182": "Ru_182",
        "183": "Ru_183",
        "184": "Ru_184",
        "185": "Ru_185",
        "186": "Ru_186",
        "187": "Ru_187",
        "188": "Ru_188",
        "189": "Ru_189",
        "190": "Ru_190",
        "191": "Ru_191",
        "192": "Ru_192",
        "193": "Ru_193",
        "194": "Ru_194",
        "195": "Ru_195",
        "196": "Ru_196",
        "197": "Ru_197",
        "198": "Ru_198",
        "199": "Ru_199",
        "200": "Ru_200",
        "201": "Ru_201",
        "202": "Ru_202",
        "203": "Ru_203",
        "204": "Ru_204",
        "205": "Ru_205",
        "206": "Ru_206",
        "207": "Ru_207",
        "208": "Ru_208",
        "209": "Ru_209",
        "210": "Ru_210",
        "211": "Ru_211",
        "212": "Ru_212",
        "213": "Ru_213",
        "214": "Ru_214",
        "215": "Ru_215",
        "216": "Ru_216",
        "217": "Ru_217",
        "218": "Ru_218",
        "219": "Ru_219",
        "220": "Ru_220",
        "221": "Ru_221",
        "222": "Ru_222",
        "223": "Ru_223",
        "224": "Ru_224",
        "225": "Ru_225",
        "226": "Ru_226",
        "227": "Ru_227",
        "228": "Ru_228",
        "229": "Ru_229",
        "230": "Ru_230",
        "231": "Ru_231",
        "232": "Ru_232",
        "233": "Ru_233",
        "234": "Ru_234",
        "235": "Ru_235",
        "236": "Ru_236",
        "237": "Ru_237",
        "238": "Ru_238",
        "239": "Ru_239",
        "240": "Ru_240",
        "241": "Ru_241",
        "242": "Ru_242",
        "243": "Ru_243",
        "244": "Ru_244",
        "245": "Ru_245",
        "246": "Ru_246",
        "247": "Ru_247",
        "248": "Ru_248",
        "249": "Ru_249",
        "250": "Ru_250",
        "251": "Ru_251",
        "252": "Ru_252",
        "253": "Ru_253",
        "254": "Ru_254",
        "255": "Ru_255",
        "256": "Ru_256",
        "257": "Ru_257",
        "258": "Ru_258",
        "259": "Ru_259",
        "260": "Ru_260",
        "261": "Ru_261",
        "262": "Ru_262",
        "263": "Ru_263",
        "264": "Ru_264",
        "265": "Ru_265",
        "266": "Ru_266",
        "267": "Ru_267",
        "268": "Ru_268",
        "269": "Ru_269",
        "270": "Ru_270",
        "271": "Ru_271",
        "272": "Ru_272",
        "273": "Ru_273",
        "274": "Ru_274",
        "275": "Ru_275",
        "276": "Ru_276",
        "277": "Ru_277",
        "278": "Ru_278",
        "279": "Ru_279",
        "280": "Ru_280",
        "281": "Ru_281",
        "282": "Ru_282",
        "283": "Ru_283",
        "284": "Ru_284",
        "285": "Ru_285",
        "286": "Ru_286",
        "287": "Ru_287",
        "288": "Ru_288",
        "289": "Ru_289",
        "290": "Ru_290",
        "291": "Ru_291",
        "292": "Ru_292",
        "293": "Ru_293",
        "294": "Ru_294",
        "295": "Ru_295",
        "296": "Ru_296",
        "297": "Ru_297",
        "298": "Ru_298",
        "299": "Ru_299",
        "300": "Ru_300",
        "301": "Ru_301",
        "302": "Ru_302",
        "303": "Ru_303",
        "304": "Ru_304",
        "305": "Ru_305",
        "306": "Ru_306",
        "307": "Ru_307",
        "308": "Ru_308",
        "309": "Ru_309",
        "310": "Ru_310",
        "311": "Ru_311",
        "312": "Ru_312",
        "313": "Ru_313",
        "314": "Ru_314",
        "315": "Ru_315",
        "316": "Ru_316",
        "317": "Ru_317",
        "318": "Ru_318",
        "319": "Ru_319",
        "320": "Ru_320",
        "321": "Ru_321",
        "322": "Ru_322",
        "323": "Ru_323",
        "324": "Ru_324",
        "325": "Ru_325",
        "326": "Ru_326",
        "327": "Ru_327",
        "328": "Ru_328",
        "329": "Ru_329",
        "330": "Ru_330",
        "331": "Ru_331",
        "332": "Ru_332",
        "333": "Ru_333",
        "334": "Ru_334",
        "335": "Ru_335",
        "336": "Ru_336",
        "337": "Ru_337",
        "338": "Ru_338",
        "339": "Ru_339",
        "340": "Ru_340",
        "341": "Ru_341",
        "342": "Ru_342",
        "343": "Ru_343",
        "344": "Ru_344",
        "345": "Ru_345",
        "346": "Ru_346",
        "347": "Ru_347",
        "348": "Ru_348",
        "349": "Ru_349",
        "350": "Ru_350",
        "351": "Ru_351",
        "352": "Ru_352",
        "353": "Ru_353",
        "354": "Ru_354",
        "355": "Ru_355",
        "356": "Ru_356",
        "357": "Ru_357",
        "358": "Ru_358",
        "359": "Ru_359",
        "360": "Ru_360",
        "361": "Ru_361",
        "362": "Ru_362",
        "363": "Ru_363",
        "364": "Ru_364",
        "365": "Ru_365",
        "366": "Ru_366",
        "367": "Ru_367",
        "368": "Ru_368",
        "369": "Ru_369",
        "370": "Ru_370",
        "371": "Ru_371",
        "372": "Ru_372",
        "373": "Ru_373",
        "374": "Ru_374",
        "375": "Ru_375",
        "376": "Ru_376",
        "377": "Ru_377",
        "378": "Ru_378",
        "379": "Ru_379",
        "380": "Ru_380",
        "381": "Ru_381",
        "382": "Ru_382",
        "383": "Ru_383",
        "384": "Ru_384",
        "385": "Ru_385",
        "386": "Ru_386",
        "387": "Ru_387",
        "388": "Ru_388",
        "389": "Ru_389",
        "390": "Ru_390",
        "391": "Ru_391",
        "392": "Ru_392",
        "393": "Ru_393",
        "394": "Ru_394",
        "395": "Ru_395",
        "396": "Ru_396",
        "397": "Ru_397",
        "398": "Ru_398",
        "399": "Ru_399",
        "400": "Ru_400",
        "401": "Ru_401",
        "402": "Ru_402",
        "403": "Ru_403",
        "404": "Ru_404",
        "405": "Ru_405",
        "406": "Ru_406",
        "407": "Ru_407",
        "408": "Ru_408",
        "409": "Ru_409",
        "410": "Ru_410",
        "411": "Ru_411",
        "412": "Ru_412",
        "413": "Ru_413",
        "414": "Ru_414",
        "415": "Ru_415",
        "416": "Ru_416",
        "417": "Ru_417",
        "418": "Ru_418",
        "419": "Ru_419",
        "420": "Ru_420",
        "421": "Ru_421",
        "422": "Ru_422",
        "423": "Ru_423",
        "424": "Ru_424",
        "425": "Ru_425",
        "426": "Ru_426",
        "427": "Ru_427",
        "428": "Ru_428",
        "429": "Ru_429",
        "430": "Ru_430",
        "431": "Ru_431",
        "432": "Ru_432",
        "433": "Ru_433",
        "434": "Ru_434",
        "435": "Ru_435",
        "436": "Ru_436",
        "437": "Ru_437",
        "438": "Ru_438",
        "439": "Ru_439",
        "440": "Ru_440",
        "441": "Ru_441",
        "442": "Ru_442",
        "443": "Ru_443",
        "444": "Ru_444",
        "445": "Ru_445",
        "446": "Ru_446",
        "447": "Ru_447",
        "448": "Ru_448",
        "449": "Ru_449",
        "450": "Ru_450",
        "451": "Ru_451",
        "452": "Ru_452",
        "453": "Ru_453",
        "454": "Ru_454",
        "455": "Ru_455",
        "456": "Ru_456",
        "457": "Ru_457",
        "458": "Ru_458",
        "459": "Ru_459",
        "460": "Ru_460",
        "461": "Ru_461",
        "462": "Ru_462",
        "463": "Ru_463",
        "464": "Ru_464",
        "465": "Ru_465",
        "466": "Ru_466",
        "467": "Ru_467",
        "468": "Ru_468",
        "469": "Ru_469",
        "470": "Ru_470",
        "471": "Ru_471",
        "472": "Ru_472",
        "473": "Ru_473",
        "474": "Ru_474",
        "475": "Ru_475",
        "476": "Ru_476",
        "477": "Ru_477",
        "478": "Ru_478",
        "479": "Ru_479",
        "480": "Ru_480",
        "481": "Ru_481",
        "482": "Ru_482",
        "483": "Ru_483",
        "484": "Ru_484",
        "485": "Ru_485",
        "486": "Ru_486",
        "487": "Ru_487",
        "488": "Ru_488",
        "489": "Ru_489",
        "490": "Ru_490",
        "491": "Ru_491",
        "492": "Ru_492",
        "493": "Ru_493",
        "494": "Ru_494",
        "495": "Ru_495",
        "496": "Ru_496",
        "497": "Ru_497",
        "498": "Ru_498",
        "499": "Ru_499",
        "500": "Ru_500"
    },
    "Leagues": {
        "1": "Ru_League_1",
        "2": "Ru_League_2",
        "3": "Ru_League_3",
        "4": "Ru_League_4",
        "5": "Ru_League_5",
        "6": "Ru_League_6",
        "7": "Ru_League_7",
        "8": "Ru_League_8",
        "9": "Ru_League_9",
        "10": "Ru_League_10"
    },
    "LocalizationText": {
        "GAMEPLAY_ERROR": "Произошла ошибка, будет перезагрузка",
        "VIDEO_TITLE_1": "Составляйте слова",
        "VIDEO_TITLE_2": "Пользуйтесь подсказкой",
        "VIDEO_TITLE_3": "Проверяйте слова",
        "START": "Старт!",
        "GENERAL_LEVEL_RULES": "Перетаскивайте кусочки с буквами в строки, чтобы составить слова.\n - длина слов {0} букв\n - всего слов {1}\n...\n\tУдачи!",
        "CHECK_WORDS_BUTTONS": "Проверить слова",
        "VICTORY_VIEW_TITLE": "Победа!",
        "VICTORY_VIEW_DESC": "Поздравляем!\nВы выиграли этот уровень!",
        "TO_MAIN_MENU_BUTTON": "На главную",
        "NEXT_LEVEL_BUTTON": "Следующий уровень",
        "LEVEL_NUMBER": "Уровень {0}",
        "MAIN_MENU_PLAY_BUTTON": "Играть",
        "MAIN_MENU_TITLE": "Меню",
        "SETTINGS_VIEW_TITLE": "Настройки",
        "SETTINGS_SOUNDS_LABEL": "Звуки",
        "SETTINGS_BACK_BUTTON": "Назад",
        "HOW_PLAY_TITLE": "Как играть",
        "OK_BUTTON": "Хорошо",
        "LEVELS_COMPLETED_LABEL": "Пройдено уровней: ",
        "GAME_OVER_MAIN_MENU_LABEL": "Поздравляем!\nВы прошли все уровни!",
        "NO_ADS_NOW_TRY_LATER": "Сейчас нет видео, попробуйте позже.",
        "FREE_UPDATE_AFTER": "+3 через: ",
        "LEADERBOARD_TITLE": "Рейтинг",
        "VICTORY_PROMPT": "Тебе нужно прокомментировать прохождение уровня в головоломке - составление слов из кластеров букв. пройден {1} уровень, вот собранные слова: {0}. Игрок ожидает похвалы за свои старания, но не банальной и не в лоб. Я верю в твои способности, будь собой, но старайся быть кратким (5-12 слов). Можешь опираться на Михаила Елизарова (но не упоминай его)"
    }
}